hetzner_dns_tools/__init__.py
hetzner_dns_tools/hetzner_dns_helpers.py
hetzner_dns_tools/record_create.py
hetzner_dns_tools/record_delete.py
hetzner_dns_tools/record_get.py
hetzner_dns_tools/record_list.py
hetzner_dns_tools/zone_create.py
hetzner_dns_tools/zone_delete.py
hetzner_dns_tools/zone_get.py
hetzner_dns_tools/zone_list.py
hetzner_dns_tools-0.0.12.data/scripts/hetzner-dns-tools
hetzner_dns_tools-0.0.12.dist-info/LICENSE
hetzner_dns_tools-0.0.12.dist-info/METADATA
hetzner_dns_tools-0.0.12.dist-info/WHEEL
hetzner_dns_tools-0.0.12.dist-info/top_level.txt
hetzner_dns_tools-0.0.12.dist-info/RECORD
