Metadata-Version: 2.1
Name: hetzner-dns-tools
Version: 0.0.12
Summary: A simple Hetzner DNS API client for Python and Bash
Home-page: https://github.com/arcanemachine/hetzner-dns-tools
Author: Nicholas Moen
Author-email: arcanemachine@tutanota.com
License: MIT
Project-URL: Bug Tracker, https://github.com/arcanemachine/hetzner-dns-tools/issues
Platform: UNKNOWN
Classifier: Programming Language :: Python :: 3
Classifier: License :: OSI Approved :: MIT License
License-File: LICENSE
Requires-Dist: requests
